README.md
setup.py
brain/__init__.py
brain/brain_pb2.py
brain/checks.py
brain/connection.py
brain/decorators.py
brain/environment.py
brain/jobs.py
brain/queries.py
brain/static.py
brain/binary/__init__.py
brain/binary/data.py
brain/binary/decorators.py
brain/binary/filesystem.py
brain/controller/__init__.py
brain/controller/decorators.py
brain/controller/helpers.py
brain/controller/interfaces.py
brain/controller/plugins.py
brain/controller/verification.py
brain/queries/__init__.py
brain/queries/decorators.py
brain/queries/reads.py
brain/queries/writes.py
brain/telemetry/__init__.py
brain/telemetry/reads.py
brain/telemetry/writes.py
ramrodbrain.egg-info/PKG-INFO
ramrodbrain.egg-info/SOURCES.txt
ramrodbrain.egg-info/dependency_links.txt
ramrodbrain.egg-info/requires.txt
ramrodbrain.egg-info/top_level.txt