Metadata-Version: 1.2
Name: ramrodbrain
Version: 0.1.65
Summary: RethinkDB Wrapper functions
Home-page: https://github.com/ramrod-project/database-brain
Author: Dan Bauman
Maintainer: Dan Bauman
Maintainer-email: dan@bauman.space
License: MIT
Download-URL: https://github.com/ramrod-project/python-brain/archive/ramrodbrain-0.1.65.tar.gz
Platform: UNKNOWN
Classifier: License :: OSI Approved :: MIT License
Classifier: Operating System :: OS Independent
Classifier: Programming Language :: Python
Classifier: Programming Language :: Python :: 3
